MANIFEST.in
README.md
requirements.txt
setup.py
pyrallelsa/__init__.py
pyrallelsa.egg-info/PKG-INFO
pyrallelsa.egg-info/SOURCES.txt
pyrallelsa.egg-info/dependency_links.txt
pyrallelsa.egg-info/requires.txt
pyrallelsa.egg-info/top_level.txt
pyrallelsa/examples/__init__.py
pyrallelsa/examples/tsp/__init__.py
pyrallelsa/examples/tsp/cities.py