Metadata-Version: 1.0
Name: pyrallelsa
Version: 0.1.0
Summary: Framework for local parallel simulated annealing
Home-page: https://github.com/mesos-magellan/pyrallelsa
Author: Hamza Faran
Author-email: UNKNOWN
License: MIT License
Platform: UNKNOWN
